CHANGELOG.rst
DESCRIPTION.rst
MANIFEST.in
README.rst
setup.py
hcpt.egg-info/PKG-INFO
hcpt.egg-info/SOURCES.txt
hcpt.egg-info/dependency_links.txt
hcpt.egg-info/entry_points.txt
hcpt.egg-info/requires.txt
hcpt.egg-info/top_level.txt
hcptcmds/__init__.py
hcptcmds/__main__.py
hcptcmds/hcpcookie.py
hcptcmds/hcpf.py
hcptcmds/hcpinit.py
hcptcmds/hcplist.py
hcptcmds/hcpload.py
hcptcmds/hcpretention.py
hcptcmds/hcptest.py
hcptcmds/hcpunload.py
hcptcmds/init.py