Metadata-Version: 1.1
Name: hcpt
Version: 1.0.19
Summary: HCP Tool
Home-page: https://gitlab.com/simont3/hcptool
Author: Thorsten Simons
Author-email: sw@snomis.local
License: MIT
Keywords: HCP Tool Hitachi Content Platform
Platform: UNKNOWN
Classifier: Development Status :: 5 - Production/Stable
Classifier: Intended Audience :: System Administrators
Classifier: Topic :: System :: Archiving
Classifier: License :: OSI Approved :: MIT License
Classifier: Programming Language :: Python :: 3.5
Classifier: Operating System :: OS Independent
Classifier: Natural Language :: English
